odoo/addons/ssi_res_users_m2o_configurator_mixin/README.rst
odoo/addons/ssi_res_users_m2o_configurator_mixin/__init__.py
odoo/addons/ssi_res_users_m2o_configurator_mixin/__manifest__.py
odoo/addons/ssi_res_users_m2o_configurator_mixin/models/__init__.py
odoo/addons/ssi_res_users_m2o_configurator_mixin/models/mixin_res_users_m2o_configurator.py
odoo/addons/ssi_res_users_m2o_configurator_mixin/static/description/icon.png
odoo/addons/ssi_res_users_m2o_configurator_mixin/templates/res_users_m2_configurator_templates.xml
odoo14_addon_ssi_res_users_m2o_configurator_mixin-14.0.1.0.0.dist-info/METADATA
odoo14_addon_ssi_res_users_m2o_configurator_mixin-14.0.1.0.0.dist-info/WHEEL
odoo14_addon_ssi_res_users_m2o_configurator_mixin-14.0.1.0.0.dist-info/top_level.txt
odoo14_addon_ssi_res_users_m2o_configurator_mixin-14.0.1.0.0.dist-info/RECORD
